{
  "aiState": "Passive",
  "attackDelay": 100000,
  "attackRange": 0,
  "attackSkill": 0,
  "baseSpeed": 0,
  "canBePet": false,
  "defenseSkill": 0,
  "description": "Light_Desc",
  "dmgMax": 0,
  "dmgMin": 0,
  "dr": 0,
  "exp": 0,
  "flying": true,
  "fraction": "NEUTRAL",
  "friendly": true,
  "gender": "Light_Gender",
  "ht": 1,
  "maxLvl": 0,
  "name": "Light_Name",
  "name_objective": "Light_Object",
  "scriptFile": "scripts/effects/Light",
  "spriteDesc": "effects/TownLight.json",
  "walkingType": "NORMAL"
}